thonny_icontract_hypothesis-1.0.0a3.data/data/LICENSE
thonny_icontract_hypothesis-1.0.0a3.data/data/README.rst
thonny_icontract_hypothesis-1.0.0a3.data/data/requirements.txt
thonnycontrib/thonny_icontract_hypothesis/__init__.py
thonnycontrib/thonny_icontract_hypothesis/py.typed
thonny_icontract_hypothesis-1.0.0a3.dist-info/LICENSE
thonny_icontract_hypothesis-1.0.0a3.dist-info/METADATA
thonny_icontract_hypothesis-1.0.0a3.dist-info/WHEEL
thonny_icontract_hypothesis-1.0.0a3.dist-info/top_level.txt
thonny_icontract_hypothesis-1.0.0a3.dist-info/RECORD
