Metadata-Version: 2.1
Name: thonny-icontract-hypothesis
Version: 1.0.0a3
Summary: Automatically test Python code using icontract-hypothesis in Thonny.
Home-page: https://github.com/mristin/thonny-icontract-hypothesis
Author: Marko Ristin
Author-email: marko@ristin.ch
License: License :: OSI Approved :: MIT License
Keywords: design-by-contract contracts automatic testing property-based
Platform: UNKNOWN
Classifier: Programming Language :: Python :: 3.7
Classifier: Programming Language :: Python :: 3.8
Classifier: License :: OSI Approved :: MIT License
Classifier: Operating System :: OS Independent
Classifier: Framework :: Hypothesis
Classifier: Development Status :: 5 - Production/Stable
Requires-Python: >=3.7
Requires-Dist: thonny (<4,>=3)
Requires-Dist: icontract-hypothesis (<2,>=1)
Provides-Extra: dev
Requires-Dist: black (==20.8b1) ; extra == 'dev'
Requires-Dist: mypy (==0.812) ; extra == 'dev'
Requires-Dist: pylint (==2.3.1) ; extra == 'dev'
Requires-Dist: pydocstyle (<3,>=2.1.1) ; extra == 'dev'
Requires-Dist: coverage (<5,>=4.5.1) ; extra == 'dev'
Requires-Dist: docutils (<1,>=0.14) ; extra == 'dev'
